Metadata-Version: 2.1
Name: aokitools
Version: 1.3.0
Summary: Adaptive open source based kitting and ignition tools.
License: MIT License
Keywords: aokitools,aokitool
Classifier: Programming Language :: Python :: 3
License-File: LICENSE
